{
  "generated_at": "2026-01-10T19:55:46.248599",
  "platforms": {
    "macos": {
      "visual_parity": 75.18,
      "builtins_parity": 92.27,
      "websuite_parity": 70.44,
      "tests_passed": 7,
      "tests_failed": 16,
      "tests_total": 23,
      "pass_rate": 30.4,
      "test_results": [
        {
          "case_id": "new_tab",
          "type": "builtins",
          "parity": 98.36,
          "diff_pct": 1.64,
          "threshold": 15,
          "passed": true
        },
        {
          "case_id": "about",
          "type": "builtins",
          "parity": 89.95,
          "diff_pct": 10.05,
          "threshold": 15,
          "passed": true
        },
        {
          "case_id": "settings",
          "type": "builtins",
          "parity": 78.03,
          "diff_pct": 21.97,
          "threshold": 15,
          "passed": false
        },
        {
          "case_id": "chrome_rustkit",
          "type": "builtins",
          "parity": 98.03,
          "diff_pct": 1.97,
          "threshold": 15,
          "passed": true
        },
        {
          "case_id": "shelf",
          "type": "builtins",
          "parity": 96.96,
          "diff_pct": 3.04,
          "threshold": 15,
          "passed": true
        },
        {
          "case_id": "article-typography",
          "type": "websuite",
          "parity": 90.9,
          "diff_pct": 9.1,
          "threshold": 20,
          "passed": true
        },
        {
          "case_id": "card-grid",
          "type": "websuite",
          "parity": 69.55,
          "diff_pct": 30.45,
          "threshold": 15,
          "passed": false
        },
        {
          "case_id": "css-selectors",
          "type": "websuite",
          "parity": 72.9,
          "diff_pct": 27.1,
          "threshold": 15,
          "passed": false
        },
        {
          "case_id": "flex-positioning",
          "type": "websuite",
          "parity": 70.79,
          "diff_pct": 29.21,
          "threshold": 15,
          "passed": false
        },
        {
          "case_id": "form-elements",
          "type": "websuite",
          "parity": 95.47,
          "diff_pct": 4.53,
          "threshold": 12,
          "passed": true
        },
        {
          "case_id": "gradient-backgrounds",
          "type": "websuite",
          "parity": 34.61,
          "diff_pct": 65.39,
          "threshold": 15,
          "passed": false
        },
        {
          "case_id": "image-gallery",
          "type": "websuite",
          "parity": 33.21,
          "diff_pct": 66.79,
          "threshold": 10,
          "passed": false
        },
        {
          "case_id": "sticky-scroll",
          "type": "websuite",
          "parity": 59.32,
          "diff_pct": 40.68,
          "threshold": 25,
          "passed": false
        },
        {
          "case_id": "backgrounds",
          "type": "micro",
          "parity": 61.31,
          "diff_pct": 38.69,
          "threshold": 15,
          "passed": false
        },
        {
          "case_id": "bg-solid",
          "type": "micro",
          "parity": 69.73,
          "diff_pct": 30.27,
          "threshold": 15,
          "passed": false
        },
        {
          "case_id": "bg-pure",
          "type": "micro",
          "parity": 46.94,
          "diff_pct": 53.06,
          "threshold": 15,
          "passed": false
        },
        {
          "case_id": "combinators",
          "type": "micro",
          "parity": 83.86,
          "diff_pct": 16.14,
          "threshold": 15,
          "passed": false
        },
        {
          "case_id": "form-controls",
          "type": "micro",
          "parity": 92.69,
          "diff_pct": 7.31,
          "threshold": 12,
          "passed": true
        },
        {
          "case_id": "gradients",
          "type": "micro",
          "parity": 69.08,
          "diff_pct": 30.92,
          "threshold": 15,
          "passed": false
        },
        {
          "case_id": "images-intrinsic",
          "type": "micro",
          "parity": 86.65,
          "diff_pct": 13.35,
          "threshold": 10,
          "passed": false
        },
        {
          "case_id": "pseudo-classes",
          "type": "micro",
          "parity": 77.65,
          "diff_pct": 22.35,
          "threshold": 15,
          "passed": false
        },
        {
          "case_id": "rounded-corners",
          "type": "micro",
          "parity": 68.76,
          "diff_pct": 31.24,
          "threshold": 15,
          "passed": false
        },
        {
          "case_id": "specificity",
          "type": "micro",
          "parity": 84.47,
          "diff_pct": 15.53,
          "threshold": 15,
          "passed": false
        }
      ],
      "parity": 75.18,
      "parity_source": "pixel_diff",
      "last_updated": "2026-01-08T22:17:35.660741",
      "issue_clusters": {
        "sizing_layout": 0,
        "paint": 0,
        "text": 0,
        "images": 0
      },
      "tier_a_pass_rate": 1.0,
      "git_commit": "520184b",
      "perf_grade": "?"
    },
    "windows": null,
    "linux": null
  },
  "history": [
    {
      "date": "2026-01-10",
      "macos": 75.18,
      "windows": 89.8,
      "linux": 79.0,
      "perf": {
        "engine_init_ms": 4.55,
        "render_time_ms": 11.3
      }
    }
  ],
  "overall": {
    "parity": 75.2,
    "perf_grade": "?"
  }
}